lotr_sdk/__init__.py
lotr_sdk/client.py
lotr_sdk/resources.py
lotr_sdk/utils.py
lotr_sdk/version.py
interview_6823bb0acd1b4ca8a37a2e052ac5dce2-0.0.2.dist-info/LICENSE.txt
interview_6823bb0acd1b4ca8a37a2e052ac5dce2-0.0.2.dist-info/METADATA
interview_6823bb0acd1b4ca8a37a2e052ac5dce2-0.0.2.dist-info/WHEEL
interview_6823bb0acd1b4ca8a37a2e052ac5dce2-0.0.2.dist-info/top_level.txt
interview_6823bb0acd1b4ca8a37a2e052ac5dce2-0.0.2.dist-info/RECORD
